canonicalwebteam/__init__.py
canonicalwebteam/flask_base/__init__.py
canonicalwebteam/flask_base/app.py
canonicalwebteam/flask_base/context.py
canonicalwebteam/flask_base/converters.py
canonicalwebteam/flask_base/decorators.py
canonicalwebteam/flask_base/env.py
canonicalwebteam/flask_base/log_utils.py
canonicalwebteam/flask_base/worker.py
canonicalwebteam/flask_base/middlewares/__init__.py
canonicalwebteam/flask_base/middlewares/dev_log.py
canonicalwebteam/flask_base/middlewares/proxy_fix.py
canonicalwebteam/flask_base/opentelemetry/__init__.py
canonicalwebteam/flask_base/opentelemetry/metrics.py
canonicalwebteam/flask_base/opentelemetry/tracing.py
canonicalwebteam_flask_base-3.1.1.dist-info/licenses/LICENSE
tests/__init__.py
tests/test_flask_base.py
tests/test_helpers.py
tests/test_log_utils.py
tests/test_metrics.py
tests/test_tracing.py
canonicalwebteam_flask_base-3.1.1.dist-info/METADATA
canonicalwebteam_flask_base-3.1.1.dist-info/WHEEL
canonicalwebteam_flask_base-3.1.1.dist-info/top_level.txt
canonicalwebteam_flask_base-3.1.1.dist-info/RECORD
