Metadata-Version: 2.4
Name: canonicalwebteam.flask-base
Version: 3.1.1
Summary: Flask extension that applies common configurationsto all of webteam's flask apps.
Home-page: https://github.com/canonical-web-and-design/canonicalwebteam.flask-base
Author: Canonical webteam
Author-email: webteam@canonical.com
Classifier: License :: OSI Approved :: Apache Software License
Classifier: Intended Audience :: Developers
Classifier: Natural Language :: English
Classifier: Topic :: Internet :: WWW/HTTP :: WSGI
Classifier: Topic :: Internet :: WWW/HTTP :: WSGI :: Application
Classifier: Topic :: Internet :: WWW/HTTP :: WSGI :: Middleware
Classifier: Programming Language :: Python :: 3.10
Classifier: Programming Language :: Python :: 3.12
Requires-Python: >=3.10
License-File: LICENSE
Requires-Dist: canonicalwebteam.yaml-responses[flask]<2,>=1
Requires-Dist: Werkzeug
Requires-Dist: flask
Requires-Dist: gunicorn
Requires-Dist: gevent
Requires-Dist: statsd
Requires-Dist: flask-compress==1.17
Requires-Dist: rich
Requires-Dist: python-json-logger
Requires-Dist: opentelemetry-api
Requires-Dist: opentelemetry-exporter-otlp
Requires-Dist: opentelemetry-exporter-otlp-proto-http
Requires-Dist: opentelemetry-instrumentation
Requires-Dist: opentelemetry-instrumentation-wsgi
Requires-Dist: opentelemetry-instrumentation-flask
Requires-Dist: opentelemetry-instrumentation-requests
Requires-Dist: opentelemetry-sdk
Dynamic: author
Dynamic: author-email
Dynamic: classifier
Dynamic: description
Dynamic: description-content-type
Dynamic: home-page
Dynamic: license-file
Dynamic: requires-dist
Dynamic: requires-python
Dynamic: summary
